namespace_kube/__init__.py
namespace_kube/namespace.py
namespace_kube-0.1.0.dist-info/METADATA
namespace_kube-0.1.0.dist-info/WHEEL
namespace_kube-0.1.0.dist-info/top_level.txt
namespace_kube-0.1.0.dist-info/RECORD
