Metadata-Version: 2.1
Name: namespace-kube
Version: 0.1.0
Summary: find namespace in running pod
Home-page: UNKNOWN
Author: YYT
License: MIT
Platform: UNKNOWN
